{
  "downloadable": true,
  "genre": "ukK6QL9gRNCfaMIlAZkbn",
  "src": "https://res.cloudinary.com/dyt6izhug/video/upload/v1587938836/Min_Etta_-_Deep_Cries_madeofgodtv.blogspot.com_puqsqv.mp3",
  "update": "2020-04-26T21:58:24.854Z",
  "position": 0,
  "profile": "RaM3pQFJQj8D3Rwns0vws",
  "slug": "MIN ETTA - DEEP CRIES OUT",
  "thumbnail": "https://res.cloudinary.com/dyt6izhug/image/upload/v1587938585/IMG-20180427-WA0022_cvtki8.jpg",
  "seo_keywords": "MIN ETTA - DEEP CRIES OUT",
  "date": "Sunday April 26th, 2020",
  "seo_title": "MIN ETTA - DEEP CRIES OUT",
  "title": "MIN ETTA - DEEP CRIES OUT",
  "seo_description": "Everyone calls out to God,who knows him?,who is he? What's his role in my life?,what can he do?, why does he do the things he does? just so many things to know about him.\n\nDEEP CRIES OUT is a piece for the season indeed,as you seek God he'll show himself to you.",
  "id": "_1dHpnHnLVbSQgh35heSH",
  "description": "<!--StartFragment-->\n\nEveryone calls out to God,who knows him?,who is he? What's his role in my life?,what can he do?, why does he do the things he does? just so many things to know about him.\n\nDEEP CRIES OUT is a piece for the season indeed,as you seek God he'll show himself to you.\n\n\n\n<!--EndFragment-->"
}